ponominalu
