Metadata-Version: 1.0
Name: python-ponominalu
Version: 0.0.4
Summary: Python client for Ponominalu API.
Home-page: https://github.com/abogoyavlensky/python-ponominalu
Author: Andrey Bogoyavlensky
Author-email: abogoyavlensky@gmail.com
License: MIT
Keywords: ponominalu
Platform: any
